pydiogment/__init__.py
pydiogment/auga.py
pydiogment/augf.py
pydiogment/augt.py
pydiogment/utils/__init__.py
pydiogment/utils/filters.py
pydiogment/utils/io.py
tests/__init__.py
tests/test_auga.py
tests/test_augf.py
tests/test_augt.py
tests/test_utils.py
pydiogment-0.1.0.dist-info/LICENSE
pydiogment-0.1.0.dist-info/METADATA
pydiogment-0.1.0.dist-info/WHEEL
pydiogment-0.1.0.dist-info/top_level.txt
pydiogment-0.1.0.dist-info/RECORD
