Metadata-Version: 2.1
Name: pydiogment
Version: 0.1.0
Summary: Python audio augmentation
Home-page: https://github.com/SuperKogito/pydiogment
Author: SuperKogito, HMMalek
Author-email: superkogito@gmail.com, hasna.m.malek@gmail.com
License: BSD
Platform: any
Classifier: Development Status :: 3 - Alpha
Classifier: Environment :: Console
Classifier: Environment :: Web Environment
Classifier: Intended Audience :: Developers
Classifier: License :: OSI Approved :: BSD License
Classifier: Operating System :: OS Independent
Classifier: Programming Language :: Python
Classifier: Topic :: Documentation
Classifier: Topic :: Utilities
Requires-Python: >=3.5
Requires-Dist: numpy (>=1.17.2)
Requires-Dist: scipy (>=1.3.1)
